ledfx/__init__.py
ledfx/__main__.py
ledfx/color.py
ledfx/config.py
ledfx/consts.py
ledfx/core.py
ledfx/events.py
ledfx/http.py
ledfx/utils.py
ledfx/api/__init__.py
ledfx/api/config.py
ledfx/api/device.py
ledfx/api/device_effects.py
ledfx/api/devices.py
ledfx/api/effect.py
ledfx/api/info.py
ledfx/api/schema.py
ledfx/api/utils.py
ledfx/api/websocket.py
ledfx/devices/__init__.py
ledfx/devices/e131.py
ledfx/devices/udp.py
ledfx/effects/__init__.py
ledfx/effects/audio.py
ledfx/effects/beat.py
ledfx/effects/energy.py
ledfx/effects/gradient.py
ledfx/effects/math.py
ledfx/effects/mel.py
ledfx/effects/pitchSpectrum.py
ledfx/effects/rainbow.py
ledfx/effects/scroll.py
ledfx/effects/spectrum.py
ledfx/effects/temporal.py
ledfx/effects/wavelength.py
ledfx_frontend/3b38551e8c65303682cb2dd770ce2618.png
ledfx_frontend/__init__.py
ledfx_frontend/bundle.js
ledfx_frontend/index.html
ledfx_frontend/ledfx_icon.png
ledfx_frontend/style.css
dintskirveli_ledfx-0.7.dist-info/AUTHORS.rst
dintskirveli_ledfx-0.7.dist-info/LICENSE.txt
dintskirveli_ledfx-0.7.dist-info/METADATA
dintskirveli_ledfx-0.7.dist-info/WHEEL
dintskirveli_ledfx-0.7.dist-info/entry_points.txt
dintskirveli_ledfx-0.7.dist-info/top_level.txt
dintskirveli_ledfx-0.7.dist-info/RECORD
