Metadata-Version: 2.1
Name: dintskirveli-ledfx
Version: 0.7
Summary: A network based light effect controller
Home-page: http://github.com/ahodges9/ledfx
Author: Austin Hodges
Author-email: austin.b.hodges@gmail.com
License: The MIT License
Platform: any
Classifier: Development Status :: 2 - Pre-Alpha
Classifier: Programming Language :: Python
Requires-Python: >=3.6.0
Requires-Dist: numpy (>=1.13.3)
Requires-Dist: voluptuous (==0.11.1)
Requires-Dist: pyaudio (>=0.2.11)
Requires-Dist: sacn (==1.3)
Requires-Dist: aiohttp (==3.3.2)
Requires-Dist: aiohttp-jinja2 (==1.0.0)
Requires-Dist: pyyaml (<4,>=3.11)
Requires-Dist: aubio (>=0.4.8)
Requires-Dist: pypiwin32 (>=223) ; platform_system == "Windows"
